LICENSE
README.md
setup.py
brightness/__init__.py
brightness/__main__.py
brightness.egg-info/PKG-INFO
brightness.egg-info/SOURCES.txt
brightness.egg-info/dependency_links.txt
brightness.egg-info/top_level.txt