Metadata-Version: 2.1
Name: brightness
Version: 0.0.1
Summary: The effortless solution for managing screen brightness in Python.
Home-page: https://github.com/ekinpy/brightness
Author: Ekin Aksu
License: MIT License
Keywords: windows,screen,brightness
Classifier: Development Status :: 4 - Beta
Classifier: Intended Audience :: Developers
Classifier: Operating System :: Microsoft :: Windows
Classifier: Programming Language :: Python :: 3
Classifier: Programming Language :: Python :: 3.8
Classifier: Programming Language :: Python :: 3.9
Classifier: Programming Language :: Python :: 3.10
Classifier: Programming Language :: Python :: 3.11
License-File: LICENSE
